LanguageMemory/__init__.py
LanguageMemory/brain.py
LanguageMemory/cli.py
LanguageMemory/dbs.py
LanguageMemory/llm.py
LanguageMemory/orchestrators.py
LanguageMemory/prompts.py
LanguageMemory/py.typed
LanguageMemory/states.py
LanguageMemory/vectorDB.py
LanguageMemory/workers.py
languagememory-1.0.3.dist-info/METADATA
languagememory-1.0.3.dist-info/WHEEL
languagememory-1.0.3.dist-info/entry_points.txt
languagememory-1.0.3.dist-info/licenses/LICENSE
languagememory-1.0.3.dist-info/RECORD
